[
  {
    "name": "黄埔街道",
    "center": "113.440241,23.098147"
  },
  {
    "name": "文冲街道",
    "center": "113.463988,23.111577"
  },
  {
    "name": "萝岗街道",
    "center": "113.505294,23.169919"
  },
  {
    "name": "九佛街道",
    "center": "113.578879,23.291597"
  },
  {
    "name": "红山街道",
    "center": "113.490542,23.081182"
  },
  {
    "name": "夏港街道",
    "center": "113.526206,23.043083"
  },
  {
    "name": "穗东街道",
    "center": "113.497516,23.083749"
  },
  {
    "name": "大沙街道",
    "center": "113.471259,23.116112"
  },
  {
    "name": "南岗街道",
    "center": "113.566799,23.092588"
  },
  {
    "name": "长岭街道",
    "center": "113.519485,23.240908"
  },
  {
    "name": "长洲街道",
    "center": "113.404891,23.063722"
  },
  {
    "name": "龙湖街道",
    "center": "113.514782,23.329926"
  },
  {
    "name": "新龙镇",
    "center": "113.568822,23.309051"
  },
  {
    "name": "鱼珠街道",
    "center": "113.440241,23.098147"
  },
  {
    "name": "云埔街道",
    "center": "113.486397,23.137116"
  },
  {
    "name": "联和街道",
    "center": "113.431753,23.250438"
  },
  {
    "name": "永和街道",
    "center": "113.535811,23.224243"
  }
]